{"contribute_index.md":"Do9tNz26","exercises_char1.md":"BLzWBE_H","exercises_char2.md":"Bp7i-L6v","exercises_char3.md":"91HyA5IL","exercises_char4-1.md":"BFG9aSqb","exercises_char4-2.md":"DptZ9uZq","exercises_char5.md":"BS0GO6NE","exercises_char6.md":"COELc3u0","exercises_char7.md":"B7JKz7aV","exercises_char8.md":"DPyzbzFF","exercises_index.md":"DXLXtpsb","extras_index.md":"B8qlk4YR","extras_memories_3-years-later.md":"DLl5PK6Y","extras_memories_after-store.md":"CIU5zEZq","extras_memories_index.md":"BhgeuxBC","extras_notes_formula-char7-char8.md":"zJTmqWPf","extras_notes_index.md":"BSsSdyGk","extras_notes_trick-for-char2.md":"DbISh2N_","index.md":"BzuoYfjY"}
